carlson_leaf_area_index/__init__.py
carlson_leaf_area_index/carlson_leaf_area_index.py
carlson_leaf_area_index/version.py
carlson_leaf_area_index-1.1.0.dist-info/licenses/LICENSE
tests/test_carlson_leaf_area_index_verification.py
tests/test_import_carlson_leaf_area_index.py
tests/test_import_dependencies.py
carlson_leaf_area_index-1.1.0.dist-info/METADATA
carlson_leaf_area_index-1.1.0.dist-info/WHEEL
carlson_leaf_area_index-1.1.0.dist-info/top_level.txt
carlson_leaf_area_index-1.1.0.dist-info/RECORD
