Metadata-Version: 2.4
Name: carlson-leaf-area-index
Version: 1.1.0
Summary: Leaf Area Index (LAI) Remote Sensing Method from Carlson et al 1997 Python Package
Author-email: Gregory Halverson <gregory.h.halverson@jpl.nasa.gov>
Project-URL: Homepage, https://github.com/JPL-Evapotranspiration-Algorithms/carlson-leaf-area-index
Classifier: Programming Language :: Python :: 3
Classifier: Operating System :: OS Independent
Requires-Python: >=3.10
License-File: LICENSE
Requires-Dist: ECOv002-calval-tables
Requires-Dist: numpy
Requires-Dist: pandas
Requires-Dist: rasters
Requires-Dist: seaborn
Provides-Extra: dev
Requires-Dist: build; extra == "dev"
Requires-Dist: pytest>=6.0; extra == "dev"
Requires-Dist: pytest-cov; extra == "dev"
Requires-Dist: jupyter; extra == "dev"
Requires-Dist: pytest; extra == "dev"
Requires-Dist: twine; extra == "dev"
Dynamic: license-file
